ntxpred2/python_scripts/__init__.py
ntxpred2/python_scripts/ntxpred2.py
ntxpred2-1.1.dist-info/LICENSE.txt
ntxpred2-1.1.dist-info/METADATA
ntxpred2-1.1.dist-info/WHEEL
ntxpred2-1.1.dist-info/entry_points.txt
ntxpred2-1.1.dist-info/top_level.txt
ntxpred2-1.1.dist-info/RECORD
