Metadata-Version: 2.2
Name: ntxpred2
Version: 1.1
Summary: NTxPred2: A method for predicting the neurotoxic activity of peptides and proteins.
Home-page: https://github.com/raghavagps/NTxPred2
Author: Anand Singh Rathore
Author-email: anandr@iiitd.ac.in, anandrathoreindia@gmail.com
License: LICENSE.txt
Requires-Python: >=3.9
License-File: LICENSE.txt
Dynamic: author
Dynamic: author-email
Dynamic: description
Dynamic: description-content-type
Dynamic: home-page
Dynamic: license
Dynamic: requires-python
Dynamic: summary
